{
  "action_state": "<SQEquippableActionState.IDLE: 0>",
  "actor_guid": {},
  "actor_instance_guid": {},
  "adjust_ads_sight_item_anim_pos": 0.0,
  "adjust_ads_sight_item_anim_pos_alpha": 1.0,
  "adjustable_sight_item_pos": 0,
  "ads_move_speed_multiplier": 0.699999988079071,
  "aiming_down_sights": false,
  "alt_use_anim": "None",
  "always_relevant": false,
  "ammo_per_rearm_item": 2.0,
  "attachment_classes": [],
  "attachments": [],
  "auto_destroy_when_finished": false,
  "bullet_count_incrementer": 0,
  "cached_adjust_ads_sight_item_anim_pos": 0.0,
  "cached_aim_prone_bobbing": false,
  "cached_delta_time": 0.0,
  "cached_equip_duration": 0.0,
  "cached_has_movement": false,
  "cached_is_bipod_deployed": false,
  "cached_is_leaning_left": false,
  "cached_is_leaning_right": false,
  "cached_is_pulling_trigger": false,
  "cached_last_zeroing_play_time": 0.0,
  "cached_last_zeroing_position": 0,
  "cached_last_zeroing_time": 0.0,
  "cached_move_bobbing": false,
  "cached_pip_scope": "None",
  "cached_soldier1p_anim_instance": "None",
  "cached_soldier3p_anim_instance": "None",
  "cached_sprint_bobbing": false,
  "cached_unequip_duration": 0.0,
  "cached_weapon1p_anim_instance": "None",
  "cached_weapon3p_anim_instance": "None",
  "calculated_ads_time": 0.0,
  "can_be_damaged": true,
  "cannot_rearm": false,
  "change_dormancy_on_equip_state": true,
  "content_bundle_guid": {},
  "current_fire_mode": 0,
  "current_fov": 0.0,
  "current_muzzle_effect": "None",
  "current_shell_ejection_effect": "None",
  "current_state": "<SQWeaponState.IDLE: 0>",
  "custom1_anim": "None",
  "custom2_anim": "None",
  "custom3_anim": "None",
  "custom_time_dilation": 1.0,
  "debug_item_static_info_class": "None",
  "display_name": "KLS",
  "dynamic_first_person_mesh_materials": [],
  "enable_auto_lod_generation": true,
  "equip_anim": "None",
  "equip_duration": 1.4299999475479126,
  "equip_state": "<SQEquippableState.NONE: 0>",
  "find_camera_component_when_view_target": true,
  "fire_input": false,
  "fire_sway_selector": false,
  "fixed_zoom_fov": false,
  "focus_additional_zoom": 20.0,
  "focus_zoom_alpha": 0.0,
  "focus_zoom_time": 0.5170000195503235,
  "fov_shader_name": "FOV State",
  "generate_overlap_events_during_level_streaming": false,
  "hidden": false,
  "hold_breath_ease_timeline": "'/Game/Blueprints/Items/Rifles/BP_KLS.Default__BP_KLS_C:HoldBreathEaseTimelineComp' Class 'TimelineComponent'>",
  "holding_breath_sway_factor": 0.0,
  "holding_zoom_easing": {
    "acceleration": 10.0,
    "opposite_acceleration": 10.0,
    "position": 0.0,
    "target": 0.0,
    "velocity": 0.0
  },
  "holding_zoom_easing_alpha": 0.0,
  "hud_selected_texture": "'/Game/UI/HUD/Inventory/Weapons/Rifles/akm.akm' Class 'Texture2D'>",
  "hud_texture": "'/Game/UI/HUD/Inventory/inventory_category_rifle.inventory_category_rifle' Class 'Texture2D'>",
  "idle_anim": "None",
  "initial_life_span": 0.0,
  "instigator": "None",
  "is3p_using_squad_sound_node_looping": true,
  "is_holding_breath": false,
  "is_modifying_zeroing": false,
  "is_round_in_chamber": true,
  "item_count": 0,
  "item_count_icon_texture": "None",
  "item_description": "Magazine Capacity: 30+1/Caliber: 7.62x39mm/Rate of Fire: 600 RPM/Fire Mode: Semi, Auto",
  "item_static_info_class": "'/Game/Blueprints/Items/Rifles/StaticInfo/BP_AKMS_StaticInfo.BP_AKMS_StaticInfo_C' Class 'BlueprintGeneratedClass'>",
  "last_shot_info": {
    "armor_damage_multiplier": 1.0,
    "is_tracer": false,
    "origin": {
      "x": 0.0,
      "y": 0.0,
      "z": 0.0
    },
    "penetration_damage_multiplier": 0.0,
    "shoot_dir": {
      "x": 0.0,
      "y": 0.0,
      "z": 0.0
    },
    "shot_counter": 0,
    "world_time": 0.0
  },
  "last_zoom_progress_at_toggle": 0.0,
  "lean_blend_out_time_multiplier": 0.800000011920929,
  "lean_completed_after_percent_of_anim": 0.75,
  "life_span": 0.0,
  "magazines": [],
  "max_item_count": 0,
  "max_time_to_loop_particles_after_last_fire": 0.5,
  "max_time_to_loop_sounds_after_last_fire": 0.5,
  "mesh1p": "'/Game/Blueprints/Items/Rifles/BP_KLS.Default__BP_KLS_C:WeaponMesh1P' Class 'SkeletalMeshComponent'>",
  "mesh3p": "'/Game/Blueprints/Items/Rifles/BP_KLS.Default__BP_KLS_C:WeaponMesh3P' Class 'SkeletalMeshComponentBudgeted'>",
  "min_net_update_frequency": 2.0,
  "modified_dry_reload_duration": 0.0,
  "modified_tactical_reload_duration": 0.0,
  "net_cull_distance_squared": 225000000.0,
  "net_dormancy": "<NetDormancy.DORM_AWAKE: 1>",
  "net_priority": 1.0,
  "net_update_frequency": 2.0,
  "net_use_owner_relevancy": true,
  "new_adjust_ads_sight_item_anim_pos": 0.0,
  "on_pawn_owner_changed_event": "<Multicast delegate 'OnPawnOwnerChangedEvent' <Unbound>>",
  "on_projectile_spawned": "<Multicast delegate 'OnProjectileSpawned' <Unbound>>",
  "only_relevant_to_owner": false,
  "pawn_owner": "None",
  "pending_fire": false,
  "pivot_offset": {
    "x": 0.0,
    "y": 0.0,
    "z": 0.0
  },
  "post_alt_use_anim": "None",
  "post_use_anim": "None",
  "pre_alt_use_anim": "None",
  "pre_fire_sway_selector": false,
  "pre_use_anim": "None",
  "prev_fov_shader_name": "Prev FOV State",
  "rearm_counter_multiplier": 1.0,
  "rearm_types_allowed": 255,
  "recoil_alignment_grip_current_offset": {
    "x": 1.0,
    "y": 0.0,
    "z": 0.0
  },
  "recoil_alignment_grip_target_offset": {
    "x": 1.0,
    "y": 0.0,
    "z": 0.0
  },
  "recoil_alignment_mult": 0.0,
  "recoil_alignment_new_grip_alignment": {
    "pitch": 0.0,
    "roll": 0.0,
    "yaw": 0.0
  },
  "recoil_alignment_new_shoulder_alignment": {
    "pitch": 0.0,
    "roll": 0.0,
    "yaw": 0.0
  },
  "recoil_alignment_shoulder_current_offset": {
    "x": 1.0,
    "y": 0.0,
    "z": 0.0
  },
  "recoil_alignment_shoulder_target_offset": {
    "x": 1.0,
    "y": 0.0,
    "z": 0.0
  },
  "recoil_grip_alignment_timeline": "'/Game/Blueprints/Items/Rifles/BP_KLS.Default__BP_KLS_C:RecoilGripAlignmentTimeline' Class 'TimelineComponent'>",
  "recoil_magnitude": 0.0,
  "recoil_shoulder_alignment_timeline": "'/Game/Blueprints/Items/Rifles/BP_KLS.Default__BP_KLS_C:RecoilShoulderAlignmentTimeline' Class 'TimelineComponent'>",
  "replicate_using_registered_sub_object_list": false,
  "replicates": true,
  "root_component": "'/Game/Blueprints/Items/Rifles/BP_KLS.Default__BP_KLS_C:SceneComponent' Class 'SceneComponent'>",
  "show_ammo_data_in_hud": false,
  "show_item_count_in_inventory": false,
  "show_mag_count_in_inventory": true,
  "simulated_ads_alpha": 1.0,
  "spawn_collision_handling_method": "<SpawnActorCollisionHandlingMethod.ALWAYS_SPAWN: 1>",
  "sprint_blendspace": "None",
  "sprite_scale": 1.0,
  "stand_anim": "None",
  "starting_sound1p": "None",
  "starting_sound3p": "None",
  "stop_adspp_drawing": false,
  "suppression_info_class_override": "'/Game/Blueprints/Items/Projectiles/SuppressionInfo/Projectile_Suppression_LMG.Projectile_Suppression_LMG_C' Class 'BlueprintGeneratedClass'>",
  "tags": [],
  "time_since_last_zoom_toggle": 0.0,
  "unequip_anim": "None",
  "unequip_duration": 1.4329999685287476,
  "unequipped_net_update_rate": 1.0,
  "use_anim": "None",
  "use_owner_as_master_pose": false,
  "use_stop_adspp_drawing": false,
  "walk_forward_anim": "None",
  "weapon_config": {
    "ads_post_transition_ratio": 0.6000000238418579,
    "allow_round_in_chamber": true,
    "allow_single_load": false,
    "allow_zoom": true,
    "armor_penetration_depth_curve": "None",
    "armor_penetration_depth_millimeters": 5,
    "barrel_socket_name": "BarrelStart",
    "can_reload_when_equipping": false,
    "create_projectile_on_server": false,
    "damage_fall_off_rate": 88.0,
    "damage_falloff_curve": "'/Game/Gameplay/DamageCurves/AKM_DamageCurve.AKM_DamageCurve' Class 'CurveFloat'>",
    "distance_to_start_damage_fall_off": 9000.0,
    "dry_reload_duration": 4.599999904632568,
    "dynamic_moa_decay_multiplier": 1.0,
    "dynamic_moa_gain_multiplier": 1.0,
    "empty_mag_to_reload": false,
    "finish_reload_grace_period": 0.0,
    "firemodes": [
      1,
      -1
    ],
    "infinite_ammo": false,
    "infinite_mags": false,
    "is_barrel_socket_on_soldier": false,
    "mag_must_be_empty_for_vehicle_rearm": false,
    "max_damage_to_apply": 60.0,
    "max_mags": 7,
    "maximum_trace_distance": 5000.0,
    "min_damage_to_apply": 35.0,
    "minimum_time_between_rearms": 0.0,
    "moa": 4.0,
    "moa_curve": "None",
    "muzzle_velocity": 71500.0,
    "projectile_camera_relative_offset_multiplier": 0.6666666865348816,
    "projectile_class": "'/Game/Blueprints/Items/Projectiles/BP_Projectile_7_62mm.BP_Projectile_7_62mm_C' Class 'BlueprintGeneratedClass'>",
    "rearm_can_fill_current_magazine": false,
    "rearm_only_if_current_magazine_is_empty": false,
    "rearm_only_one_magazine": false,
    "rearm_only_x_rounds_of_ammo": false,
    "rearm_rounds_of_ammo_per_rearm": 1,
    "reload_dry_bipod_duration": 1.0,
    "reset_burst_on_trigger_release": false,
    "rounds_between_tracer": 0,
    "rounds_per_mag": 30,
    "tactical_reload_bipod_duration": 1.0,
    "tactical_reload_duration": 3.9000000953674316,
    "time_between_shots": 0.10000000149011612,
    "time_between_single_shots": 0.125,
    "time_to_start_damage_fall_off": 0.3400000035762787,
    "trace_distance_after_penetration_meters": 10.0,
    "tracer_projectile_class": "None",
    "wall_hack_check_trace_distance": 20.0
  },
  "zoomed_fov": 0.0
}